crypto_address_generator/__init__.py
crypto_address_generator/generator.py
crypto_address_generator-0.1.0.dist-info/METADATA
crypto_address_generator-0.1.0.dist-info/WHEEL
crypto_address_generator-0.1.0.dist-info/top_level.txt
crypto_address_generator-0.1.0.dist-info/RECORD
