Metadata-Version: 2.4
Name: crypto_address_generator
Version: 0.1.0
Summary: Generate BTC, LTC, ETH, and SOL addresses locally
Home-page: https://github.com/yourusername/crypto_address_generator
Author: Your Name
Requires-Python: >=3.7
Requires-Dist: bitcoinlib
Requires-Dist: eth-account
Requires-Dist: solana
Dynamic: author
Dynamic: home-page
Dynamic: requires-dist
Dynamic: requires-python
Dynamic: summary
